idflow/__init__.py
idflow/docker.py
idflow/flow.py
idflow/utils.py
invoke_tools/__init__.py
invoke_tools/ci/__init__.py
invoke_tools/ci/jenkins.py
invoke_tools/ci/travis.py
invoke_tools/cloud/__init__.py
invoke_tools/cloud/aws.py
invoke_tools/lxc/__init__.py
invoke_tools/lxc/docker.py
invoke_tools/system/__init__.py
invoke_tools/system/info.py
invoke_tools/vcs/__init__.py
invoke_tools/vcs/git_scm.py
invoke_tools-0.2.2.dist-info/DESCRIPTION.rst
invoke_tools-0.2.2.dist-info/METADATA
invoke_tools-0.2.2.dist-info/RECORD
invoke_tools-0.2.2.dist-info/WHEEL
invoke_tools-0.2.2.dist-info/metadata.json
invoke_tools-0.2.2.dist-info/top_level.txt
tests/__init__.py
tests/ci/__init__.py
tests/ci/jenkins_test.py
tests/cloud/__init__.py
tests/lxc/__init__.py
tests/system/__init__.py
tests/vcs/__init__.py
tests/vcs/git_scm_test.py
